[
  {
    "id": "b2_konjunktiv",
    "title": "Konjunktiv II",
    "level": "B2",
    "description": "Hypothetical situations, polite requests and unreal conditions — the subjunctive mood",
    "xpReward": 30,
    "words": [
      { "german": "Wenn ich reich wäre", "english": "If I were rich", "roman": "ven ikh raikh väh-ruh", "example": "Wenn ich reich wäre, würde ich die Welt bereisen.", "exampleTrans": "If I were rich I would travel the world.", "category": "konjunktiv" },
      { "german": "Ich würde gern reisen", "english": "I would like to travel", "roman": "ikh vür-duh gern rai-zen", "example": "Ich würde gern nach Japan reisen.", "exampleTrans": "I would like to travel to Japan.", "category": "konjunktiv" },
      { "german": "Das wäre schön", "english": "That would be nice", "roman": "das väh-ruh shön", "example": "Ein Urlaub am Meer — das wäre wirklich schön.", "exampleTrans": "A holiday at the sea — that would really be nice.", "category": "konjunktiv" },
      { "german": "Könnten Sie mir helfen?", "english": "Could you help me? (polite)", "roman": "kön-ten zee meer hel-fen", "example": "Könnten Sie mir bitte mit dem Gepäck helfen?", "exampleTrans": "Could you please help me with the luggage?", "category": "konjunktiv" },
      { "german": "Ich hätte gern einen Kaffee", "english": "I would like a coffee (polite)", "roman": "ikh hä-tuh gern ai-nen ka-fey", "example": "Ich hätte gern einen Kaffee und ein Stück Kuchen.", "exampleTrans": "I would like a coffee and a slice of cake.", "category": "konjunktiv" },
      { "german": "Wenn ich Zeit hätte, würde ich kommen", "english": "If I had time I would come", "roman": "ven ikh tsait hä-tuh vür-duh ikh ko-men", "example": "Wenn ich mehr Zeit hätte, würde ich öfter kommen.", "exampleTrans": "If I had more time I would come more often.", "category": "konjunktiv" },
      { "german": "An deiner Stelle würde ich das nicht tun", "english": "In your position I would not do that", "roman": "an dai-ner shte-luh vür-duh ikh das nikht toon", "example": "An deiner Stelle würde ich das nicht tun — es ist zu riskant.", "exampleTrans": "In your position I would not do that — it is too risky.", "category": "konjunktiv" },
      { "german": "Es wäre besser, wenn", "english": "It would be better if", "roman": "es väh-ruh bes-ser ven", "example": "Es wäre besser, wenn du früher aufstehst.", "exampleTrans": "It would be better if you got up earlier.", "category": "konjunktiv" },
      { "german": "Ich wünschte, ich wäre dabei gewesen", "english": "I wish I had been there", "roman": "ikh vünsh-tuh ikh väh-ruh dah-bai guh-vey-zen", "example": "Ich wünschte, ich wäre bei der Party dabei gewesen.", "exampleTrans": "I wish I had been at the party.", "category": "konjunktiv" },
      { "german": "Hättest du das gewusst?", "english": "Would you have known that?", "roman": "hä-test doo das guh-voost", "example": "Hättest du das gewusst, ohne es nachzulesen?", "exampleTrans": "Would you have known that without looking it up?", "category": "konjunktiv" },
      { "german": "Wenn er früher gekommen wäre", "english": "If he had come earlier", "roman": "ven air frü-er guh-ko-men väh-ruh", "example": "Wenn er früher gekommen wäre, hätten wir ihn getroffen.", "exampleTrans": "If he had come earlier we would have met him.", "category": "konjunktiv" },
      { "german": "Das hätte ich nicht erwartet", "english": "I would not have expected that", "roman": "das hä-tuh ikh nikht er-var-tet", "example": "Das hätte ich wirklich nicht erwartet — eine große Überraschung.", "exampleTrans": "I really would not have expected that — a big surprise.", "category": "konjunktiv" },
      { "german": "Wäre ich doch zu Hause geblieben", "english": "If only I had stayed home", "roman": "väh-ruh ikh dokh tsoo how-zuh guh-blee-ben", "example": "Wäre ich doch zu Hause geblieben statt in den Regen zu gehen.", "exampleTrans": "If only I had stayed home instead of going out in the rain.", "category": "konjunktiv" },
      { "german": "Sie sollten das überdenken", "english": "You should reconsider that (formal polite)", "roman": "zee zol-ten das ü-ber-den-ken", "example": "Sie sollten das noch einmal überdenken, bevor Sie entscheiden.", "exampleTrans": "You should reconsider that once more before you decide.", "category": "konjunktiv" },
      { "german": "Das dürfte nicht schwer sein", "english": "That should not be difficult", "roman": "das dür-ftuh nikht shvair zain", "example": "Das dürfte nicht schwer sein für jemanden mit deiner Erfahrung.", "exampleTrans": "That should not be difficult for someone with your experience.", "category": "konjunktiv" }
    ]
  },
  {
    "id": "b2_debate",
    "title": "Debate and Opinions",
    "level": "B2",
    "description": "Argue, persuade, counter-argue and discuss complex topics in German",
    "xpReward": 30,
    "words": [
      { "german": "Ich vertrete die Ansicht, dass", "english": "I hold the view that", "roman": "ikh fer-trey-tuh dee an-zikht das", "example": "Ich vertrete die Ansicht, dass Bildung kostenlos sein sollte.", "exampleTrans": "I hold the view that education should be free.", "category": "debate" },
      { "german": "Das lässt sich nicht leugnen", "english": "That cannot be denied", "roman": "das läst zikh nikht loig-nen", "example": "Das lässt sich nicht leugnen — die Zahlen sprechen für sich.", "exampleTrans": "That cannot be denied — the numbers speak for themselves.", "category": "debate" },
      { "german": "Es gibt jedoch Gegenargumente", "english": "However there are counter-arguments", "roman": "es gibt yeh-dokh gey-gen-ar-goo-men-tuh", "example": "Es gibt jedoch Gegenargumente, die man beachten muss.", "exampleTrans": "However there are counter-arguments that must be considered.", "category": "debate" },
      { "german": "Aus meiner Sicht gesehen", "english": "From my point of view", "roman": "ows mai-ner zikht guh-zey-en", "example": "Aus meiner Sicht gesehen ist das die falsche Entscheidung.", "exampleTrans": "From my point of view that is the wrong decision.", "category": "debate" },
      { "german": "Man könnte argumentieren, dass", "english": "One could argue that", "roman": "man kön-tuh ar-goo-men-tee-ren das", "example": "Man könnte argumentieren, dass beide Seiten Recht haben.", "exampleTrans": "One could argue that both sides are right.", "category": "debate" },
      { "german": "Das greift zu kurz", "english": "That is too simplistic / That misses the point", "roman": "das graift tsoo koorts", "example": "Diese Erklärung greift zu kurz — es ist viel komplexer.", "exampleTrans": "This explanation is too simplistic — it is much more complex.", "category": "debate" },
      { "german": "Im Großen und Ganzen", "english": "By and large / On the whole", "roman": "im groh-sen oont gan-tsen", "example": "Im Großen und Ganzen war die Veranstaltung ein Erfolg.", "exampleTrans": "By and large the event was a success.", "category": "debate" },
      { "german": "Letztendlich kommt es darauf an", "english": "Ultimately it depends on", "roman": "letst-end-likh komt es dah-rowf an", "example": "Letztendlich kommt es darauf an, welche Werte man hat.", "exampleTrans": "Ultimately it depends on what values one holds.", "category": "debate" },
      { "german": "Ich bezweifle, dass", "english": "I doubt that", "roman": "ikh buh-tsvai-fluh das", "example": "Ich bezweifle, dass das eine nachhaltige Lösung ist.", "exampleTrans": "I doubt that this is a sustainable solution.", "category": "debate" },
      { "german": "Das ist eine Frage der Perspektive", "english": "That is a matter of perspective", "roman": "das ist ai-nuh frah-guh dair per-spek-tee-vuh", "example": "Ob das gerecht ist, das ist eine Frage der Perspektive.", "exampleTrans": "Whether that is fair is a matter of perspective.", "category": "debate" },
      { "german": "Nicht zu vergessen", "english": "Not to forget / Let us not forget", "roman": "nikht tsoo fer-ges-sen", "example": "Nicht zu vergessen: die Auswirkungen auf die Umwelt.", "exampleTrans": "Not to forget: the effects on the environment.", "category": "debate" },
      { "german": "Dem muss ich widersprechen", "english": "I must contradict that", "roman": "dem moos ikh vee-der-shpreh-khen", "example": "Dem muss ich klar widersprechen — das stimmt nicht.", "exampleTrans": "I must clearly contradict that — that is not correct.", "category": "debate" },
      { "german": "Das spricht für sich selbst", "english": "That speaks for itself", "roman": "das shprikht für zikh zelpst", "example": "Die Ergebnisse sind so eindeutig — das spricht für sich selbst.", "exampleTrans": "The results are so clear — that speaks for itself.", "category": "debate" },
      { "german": "Es bleibt abzuwarten, ob", "english": "It remains to be seen whether", "roman": "es blaibt ap-tsoo-var-ten op", "example": "Es bleibt abzuwarten, ob die Maßnahmen Wirkung zeigen.", "exampleTrans": "It remains to be seen whether the measures will have an effect.", "category": "debate" },
      { "german": "Alles in allem", "english": "All in all", "roman": "a-les in a-lem", "example": "Alles in allem war es eine lehrreiche Erfahrung.", "exampleTrans": "All in all it was an educational experience.", "category": "debate" }
    ]
  },
  {
    "id": "b2_workplace",
    "title": "Workplace German",
    "level": "B2",
    "description": "Professional German for meetings, emails, negotiations and office life",
    "xpReward": 30,
    "words": [
      { "german": "Ich leite diese Abteilung", "english": "I manage this department", "roman": "ikh lai-tuh dee-zuh ap-tai-loong", "example": "Ich leite diese Abteilung seit drei Jahren.", "exampleTrans": "I have been managing this department for three years.", "category": "workplace" },
      { "german": "Wir müssen die Deadline einhalten", "english": "We must meet the deadline", "roman": "veer müs-sen dee ded-lain ain-hal-ten", "example": "Wir müssen unbedingt die Deadline einhalten.", "exampleTrans": "We absolutely must meet the deadline.", "category": "workplace" },
      { "german": "Das Budget wurde überschritten", "english": "The budget was exceeded", "roman": "das boo-jet voor-duh ü-ber-shri-ten", "example": "Das Budget wurde leider um zwanzig Prozent überschritten.", "exampleTrans": "Unfortunately the budget was exceeded by twenty percent.", "category": "workplace" },
      { "german": "Können wir einen Termin vereinbaren?", "english": "Can we arrange an appointment?", "roman": "kö-nen veer ai-nen ter-meen fer-ain-bah-ren", "example": "Können wir für nächste Woche einen Termin vereinbaren?", "exampleTrans": "Can we arrange an appointment for next week?", "category": "workplace" },
      { "german": "Ich schicke Ihnen die Unterlagen zu", "english": "I will send you the documents", "roman": "ikh shik-kuh ee-nen dee oon-ter-lah-gen tsoo", "example": "Ich schicke Ihnen die Unterlagen noch heute zu.", "exampleTrans": "I will send you the documents still today.", "category": "workplace" },
      { "german": "Das Projekt liegt im Zeitplan", "english": "The project is on schedule", "roman": "das pro-yekt leegt im tsait-plan", "example": "Gute Neuigkeit — das Projekt liegt genau im Zeitplan.", "exampleTrans": "Good news — the project is exactly on schedule.", "category": "workplace" },
      { "german": "Wir brauchen eine Lösung", "english": "We need a solution", "roman": "veer brow-khen ai-nuh lö-zoong", "example": "Wir brauchen dringend eine Lösung für dieses Problem.", "exampleTrans": "We urgently need a solution for this problem.", "category": "workplace" },
      { "german": "Der Umsatz ist gestiegen", "english": "The revenue has increased", "roman": "dair oom-zats ist guh-shtee-gen", "example": "Der Umsatz ist dieses Quartal um zehn Prozent gestiegen.", "exampleTrans": "The revenue has increased by ten percent this quarter.", "category": "workplace" },
      { "german": "Ich bitte um Ihr Feedback", "english": "I request your feedback", "roman": "ikh bi-tuh oom eer feed-bek", "example": "Ich bitte um Ihr Feedback bis Ende der Woche.", "exampleTrans": "I request your feedback by the end of the week.", "category": "workplace" },
      { "german": "Das muss noch überarbeitet werden", "english": "That still needs to be revised", "roman": "das moos nokh ü-ber-ar-bai-tet ver-den", "example": "Der Bericht muss noch überarbeitet werden bevor wir ihn senden.", "exampleTrans": "The report still needs to be revised before we send it.", "category": "workplace" },
      { "german": "Wir sind zu einer Einigung gekommen", "english": "We have reached an agreement", "roman": "veer zint tsoo ai-ner ai-ni-goong guh-ko-men", "example": "Nach langen Verhandlungen sind wir zu einer Einigung gekommen.", "exampleTrans": "After long negotiations we have reached an agreement.", "category": "workplace" },
      { "german": "Das steht noch aus", "english": "That is still pending", "roman": "das shteyt nokh ows", "example": "Die Genehmigung steht leider noch aus.", "exampleTrans": "The approval is unfortunately still pending.", "category": "workplace" },
      { "german": "Ich möchte das zur Sprache bringen", "english": "I would like to bring that up", "roman": "ikh mökhte das tsoor shprah-khuh brin-gen", "example": "Ich möchte das Thema Überstunden zur Sprache bringen.", "exampleTrans": "I would like to bring up the topic of overtime.", "category": "workplace" },
      { "german": "Die Verhandlungen laufen gut", "english": "The negotiations are going well", "roman": "dee fer-hand-loong-en low-fen goot", "example": "Die Verhandlungen mit dem neuen Partner laufen gut.", "exampleTrans": "The negotiations with the new partner are going well.", "category": "workplace" },
      { "german": "Wir sind auf dem richtigen Weg", "english": "We are on the right track", "roman": "veer zint owf dem rikh-ti-gen veg", "example": "Die Zahlen zeigen es — wir sind auf dem richtigen Weg.", "exampleTrans": "The numbers show it — we are on the right track.", "category": "workplace" }
    ]
  },
  {
    "id": "b2_idioms",
    "title": "Native Expressions and Idioms",
    "level": "B2",
    "description": "Sound like a native with common German idioms and expressions",
    "xpReward": 30,
    "words": [
      { "german": "Das ist nicht mein Bier", "english": "That is not my problem (not my beer)", "roman": "das ist nikht main beer", "example": "Was er in seiner Freizeit macht, ist nicht mein Bier.", "exampleTrans": "What he does in his free time is not my problem.", "category": "idiom" },
      { "german": "Ich drücke dir die Daumen", "english": "I am keeping my fingers crossed for you", "roman": "ikh drük-kuh deer dee dow-men", "example": "Viel Erfolg bei der Prüfung — ich drücke dir die Daumen!", "exampleTrans": "Good luck with the exam — I am keeping my fingers crossed for you!", "category": "idiom" },
      { "german": "Das geht mir auf die Nerven", "english": "That gets on my nerves", "roman": "das geyt meer owf dee ner-ven", "example": "Dieses Geräusch geht mir wirklich auf die Nerven.", "exampleTrans": "This noise really gets on my nerves.", "category": "idiom" },
      { "german": "Ich verstehe nur Bahnhof", "english": "I don't understand anything (I only understand train station)", "roman": "ikh fer-shtey-uh noor bahn-hohf", "example": "Er hat so schnell geredet — ich habe nur Bahnhof verstanden.", "exampleTrans": "He spoke so fast — I did not understand a thing.", "category": "idiom" },
      { "german": "Alles hat ein Ende, nur die Wurst hat zwei", "english": "Everything has an end, only the sausage has two", "roman": "a-les hat ain en-duh noor dee voorst hat tsvai", "example": "Alles hat ein Ende, nur die Wurst hat zwei — der Urlaub ist vorbei.", "exampleTrans": "All good things come to an end — the holiday is over.", "category": "idiom" },
      { "german": "Das ist mir Wurst", "english": "I don't care (That is sausage to me)", "roman": "das ist meer voorst", "example": "Ob wir Fußball oder Tennis schauen — das ist mir Wurst.", "exampleTrans": "Whether we watch football or tennis — I don't care.", "category": "idiom" },
      { "german": "Jetzt geht's um die Wurst", "english": "Now it's do or die (now it's about the sausage)", "roman": "yetst geyts oom dee voorst", "example": "Das Finale ist morgen — jetzt geht's wirklich um die Wurst.", "exampleTrans": "The final is tomorrow — now it is really do or die.", "category": "idiom" },
      { "german": "Ich bin fix und fertig", "english": "I am completely exhausted / done", "roman": "ikh bin fiks oont fer-tikh", "example": "Nach dem langen Tag bin ich fix und fertig.", "exampleTrans": "After the long day I am completely exhausted.", "category": "idiom" },
      { "german": "Das ist nicht der Rede wert", "english": "That is not worth mentioning", "roman": "das ist nikht dair rey-duh vert", "example": "Danke fürs Helfen! — Ach, das ist nicht der Rede wert.", "exampleTrans": "Thanks for the help! — Oh, that is not worth mentioning.", "category": "idiom" },
      { "german": "Er hat einen Vogel", "english": "He is crazy (He has a bird)", "roman": "air hat ai-nen foh-gel", "example": "Er will bei minus zwanzig Grad schwimmen — der hat einen Vogel!", "exampleTrans": "He wants to swim in minus twenty degrees — he is crazy!", "category": "idiom" },
      { "german": "Das kommt mir spanisch vor", "english": "That seems strange to me (That comes across as Spanish)", "roman": "das komt meer shpah-nish for", "example": "Sein Verhalten kommt mir irgendwie spanisch vor.", "exampleTrans": "His behaviour seems somehow strange to me.", "category": "idiom" },
      { "german": "Tomaten auf den Augen haben", "english": "To be oblivious (To have tomatoes on your eyes)", "roman": "toh-mah-ten owf den ow-gen hah-ben", "example": "Siehst du das nicht? Du hast wohl Tomaten auf den Augen!", "exampleTrans": "Can you not see that? You must be completely oblivious!", "category": "idiom" },
      { "german": "Den Nagel auf den Kopf treffen", "english": "To hit the nail on the head", "roman": "den nah-gel owf den kopf tref-fen", "example": "Mit deiner Analyse hast du den Nagel auf den Kopf getroffen.", "exampleTrans": "With your analysis you have hit the nail on the head.", "category": "idiom" },
      { "german": "Ich habe die Nase voll", "english": "I am fed up (I have a full nose)", "roman": "ikh hah-buh dee nah-zuh fol", "example": "Ich habe die Nase voll von diesem Stress.", "exampleTrans": "I am fed up with this stress.", "category": "idiom" },
      { "german": "Das Leben ist kein Ponyhof", "english": "Life is not easy (Life is not a pony farm)", "roman": "das ley-ben ist kain poh-nee-hohf", "example": "Stell dich nicht so an — das Leben ist kein Ponyhof.", "exampleTrans": "Stop complaining — life is not easy.", "category": "idiom" }
    ]
  },
  {
    "id": "b2_complex_grammar",
    "title": "Complex Grammar",
    "level": "B2",
    "description": "Relative clauses, passive voice, extended participle constructions and advanced sentence structure",
    "xpReward": 35,
    "words": [
      { "german": "Das Buch, das ich lese, ist interessant", "english": "The book that I am reading is interesting (relative clause Akkusativ)", "roman": "das bookh das ikh ley-zuh ist in-tuh-re-sant", "example": "Das Buch, das ich gerade lese, ist sehr interessant.", "exampleTrans": "The book that I am currently reading is very interesting.", "category": "grammar" },
      { "german": "Der Mann, dem ich geholfen habe", "english": "The man whom I helped (relative clause Dativ)", "roman": "dair man dem ikh guh-hol-fen hah-buh", "example": "Der Mann, dem ich geholfen habe, hat sich herzlich bedankt.", "exampleTrans": "The man whom I helped thanked me warmly.", "category": "grammar" },
      { "german": "Das wird gemacht", "english": "That is being done (passive Präsens)", "roman": "das virt guh-makht", "example": "Die Reparatur wird sofort gemacht.", "exampleTrans": "The repair is being done immediately.", "category": "grammar" },
      { "german": "Das wurde gestern gemacht", "english": "That was done yesterday (passive Präteritum)", "roman": "das voor-duh ges-tern guh-makht", "example": "Die Bestellung wurde gestern aufgegeben.", "exampleTrans": "The order was placed yesterday.", "category": "grammar" },
      { "german": "Das Haus wird gebaut", "english": "The house is being built (passive)", "roman": "das hows virt guh-bowt", "example": "Das Haus in unserer Straße wird gerade gebaut.", "exampleTrans": "The house in our street is currently being built.", "category": "grammar" },
      { "german": "Es wird empfohlen, dass", "english": "It is recommended that (impersonal passive)", "roman": "es virt emp-foh-len das", "example": "Es wird empfohlen, dass man täglich Sport treibt.", "exampleTrans": "It is recommended that one does sport daily.", "category": "grammar" },
      { "german": "Das zu lösende Problem", "english": "The problem to be solved (extended participle)", "roman": "das tsoo lö-zen-duh pro-bleym", "example": "Das zu lösende Problem erfordert kreative Ideen.", "exampleTrans": "The problem to be solved requires creative ideas.", "category": "grammar" },
      { "german": "Die geplante Reise", "english": "The planned trip (participial adjective)", "roman": "dee guh-plan-tuh rai-zuh", "example": "Die geplante Reise nach Italien wurde abgesagt.", "exampleTrans": "The planned trip to Italy was cancelled.", "category": "grammar" },
      { "german": "Obwohl er müde war, arbeitete er weiter", "english": "Although he was tired he kept working (obwohl + verb end)", "roman": "op-vohl air mü-duh var ar-bai-tuh-tuh air vai-ter", "example": "Obwohl er sehr müde war, arbeitete er bis Mitternacht weiter.", "exampleTrans": "Although he was very tired he kept working until midnight.", "category": "grammar" },
      { "german": "Nachdem sie gegessen hatte, ging sie schlafen", "english": "After she had eaten she went to sleep (Plusquamperfekt)", "roman": "nakh-dem zee guh-ges-sen ha-tuh ging zee shlah-fen", "example": "Nachdem sie zu Abend gegessen hatte, ging sie schlafen.", "exampleTrans": "After she had eaten dinner she went to sleep.", "category": "grammar" },
      { "german": "Je mehr du lernst, desto besser wirst du", "english": "The more you learn the better you become", "roman": "yeh mair doo lernst des-toh bes-ser virst doo", "example": "Je mehr du übst, desto besser wirst du in der Sprache.", "exampleTrans": "The more you practise the better you become in the language.", "category": "grammar" },
      { "german": "Weder noch", "english": "Neither nor", "roman": "vey-der nokh", "example": "Er spricht weder Spanisch noch Italienisch.", "exampleTrans": "He speaks neither Spanish nor Italian.", "category": "grammar" },
      { "german": "Sowohl als auch", "english": "Both and", "roman": "zoh-vohl als owkh", "example": "Sie spricht sowohl Deutsch als auch Englisch fließend.", "exampleTrans": "She speaks both German and English fluently.", "category": "grammar" },
      { "german": "Nicht nur, sondern auch", "english": "Not only but also", "roman": "nikht noor zon-dern owkh", "example": "Er ist nicht nur intelligent, sondern auch sehr fleißig.", "exampleTrans": "He is not only intelligent but also very hardworking.", "category": "grammar" },
      { "german": "Statt zu klagen, sollte man handeln", "english": "Instead of complaining one should act (Infinitivkonstruktion)", "roman": "shtat tsoo klah-gen zol-tuh man han-deln", "example": "Statt zu klagen, sollte man einfach handeln und Lösungen suchen.", "exampleTrans": "Instead of complaining one should simply act and look for solutions.", "category": "grammar" }
    ]
  },
  {
    "id": "b2_reallife",
    "title": "Real-life Scenarios",
    "level": "B2",
    "description": "Handle complex real-life situations — legal, medical, bureaucratic and social",
    "xpReward": 35,
    "words": [
      { "german": "Ich möchte ein Konto eröffnen", "english": "I would like to open an account", "roman": "ikh mökhte ain kon-toh er-öf-nen", "example": "Ich möchte bei Ihrer Bank ein Konto eröffnen.", "exampleTrans": "I would like to open an account at your bank.", "category": "reallife" },
      { "german": "Können Sie das bitte schriftlich bestätigen?", "english": "Can you please confirm that in writing?", "roman": "kö-nen zee das bi-tuh shrift-likh buh-shtä-ti-gen", "example": "Können Sie die Zusage bitte schriftlich bestätigen?", "exampleTrans": "Can you please confirm the commitment in writing?", "category": "reallife" },
      { "german": "Ich lege Widerspruch ein", "english": "I am filing an objection / appeal", "roman": "ikh ley-guh vee-der-shprookh ain", "example": "Ich lege gegen diesen Bescheid Widerspruch ein.", "exampleTrans": "I am filing an objection against this notice.", "category": "reallife" },
      { "german": "Das steht im Widerspruch zu", "english": "That contradicts / is in conflict with", "roman": "das shteyt im vee-der-shprookh tsoo", "example": "Das steht im Widerspruch zu dem, was mir versprochen wurde.", "exampleTrans": "That contradicts what was promised to me.", "category": "reallife" },
      { "german": "Ich benötige eine Bescheinigung", "english": "I need a certificate / document", "roman": "ikh buh-nö-ti-guh ai-nuh buh-shai-ni-goong", "example": "Ich benötige eine Bescheinigung über meine Arbeitstätigkeit.", "exampleTrans": "I need a certificate confirming my employment.", "category": "reallife" },
      { "german": "Welche Unterlagen brauche ich dafür?", "english": "What documents do I need for that?", "roman": "vel-khuh oon-ter-lah-gen brow-khuh ikh dah-für", "example": "Welche Unterlagen brauche ich dafür — können Sie mir eine Liste geben?", "exampleTrans": "What documents do I need for that — can you give me a list?", "category": "reallife" },
      { "german": "Ich habe einen Termin beim Finanzamt", "english": "I have an appointment at the tax office", "roman": "ikh hah-buh ai-nen ter-meen baim fi-nants-amt", "example": "Ich habe morgen einen Termin beim Finanzamt wegen meiner Steuererklärung.", "exampleTrans": "I have an appointment at the tax office tomorrow about my tax return.", "category": "reallife" },
      { "german": "Die Krankenversicherung übernimmt die Kosten", "english": "The health insurance covers the costs", "roman": "dee kran-ken-fer-zi-khuh-roong ü-ber-nimt dee kos-ten", "example": "Die Krankenversicherung übernimmt die Kosten für die Behandlung.", "exampleTrans": "The health insurance covers the costs for the treatment.", "category": "reallife" },
      { "german": "Ich möchte das reklamieren", "english": "I would like to make a complaint / return this", "roman": "ikh mökhte das reh-klah-mee-ren", "example": "Das Produkt ist defekt — ich möchte das reklamieren.", "exampleTrans": "The product is defective — I would like to return this.", "category": "reallife" },
      { "german": "Das Mietverhältnis wird gekündigt", "english": "The tenancy is being terminated", "roman": "das meet-fer-häl-tnis virt guh-kün-digt", "example": "Das Mietverhältnis wird zum Ende des Monats gekündigt.", "exampleTrans": "The tenancy is being terminated at the end of the month.", "category": "reallife" },
      { "german": "Ich suche eine Wohnung zur Miete", "english": "I am looking for an apartment to rent", "roman": "ikh zoo-khuh ai-nuh voh-noong tsoor mee-tuh", "example": "Ich suche dringend eine Wohnung zur Miete in der Stadtmitte.", "exampleTrans": "I am urgently looking for an apartment to rent in the city centre.", "category": "reallife" },
      { "german": "Die Nebenkosten sind im Preis inbegriffen", "english": "The utilities are included in the price", "roman": "dee ney-ben-kos-ten zint im prais in-buh-grif-fen", "example": "Die Nebenkosten sind im monatlichen Preis inbegriffen.", "exampleTrans": "The utilities are included in the monthly price.", "category": "reallife" },
      { "german": "Ich brauche einen Anwalt", "english": "I need a lawyer", "roman": "ikh brow-khuh ai-nen an-valt", "example": "Die Situation ist kompliziert — ich brauche dringend einen Anwalt.", "exampleTrans": "The situation is complicated — I urgently need a lawyer.", "category": "reallife" },
      { "german": "Das Visum läuft ab", "english": "The visa is expiring", "roman": "das vee-zoom loyft ap", "example": "Mein Visum läuft nächsten Monat ab — ich muss es verlängern.", "exampleTrans": "My visa is expiring next month — I need to extend it.", "category": "reallife" },
      { "german": "Ich möchte die Staatsangehörigkeit beantragen", "english": "I would like to apply for citizenship", "roman": "ikh mökhte dee shtahts-an-guh-hö-rig-kait buh-an-trah-gen", "example": "Nach zehn Jahren möchte ich die deutsche Staatsangehörigkeit beantragen.", "exampleTrans": "After ten years I would like to apply for German citizenship.", "category": "reallife" }
    ]
  }
]
